<?xml version="1.0" encoding="UTF-8"?><?workdir /C:\develop\ws\cdo\org.eclipse.emf.cdo.doc\.temp\.intermediate\users?><?path2project ..\?><task xmlns:ditaarch="http://dita.oasis-open.org/architecture/2005/" id="working_with_resources" xml:lang="en-us" ditaarch:DITAArchVersion="1.1" domains="(topic ui-d) (topic hi-d) (topic pr-d) (topic sw-d)                          (topic ut-d) (topic indexing-d)" class="- topic/topic task/task " xtrf="..\users\working_with_resources.dita" xtrc="task:1">
	<title class="- topic/title " xtrf="..\users\working_with_resources.dita" xtrc="title:1">Working with Resources</title>
	<titlealts class="- topic/titlealts " xtrf="..\users\working_with_resources.dita" xtrc="titlealts:1">
		<navtitle class="- topic/navtitle " xtrf="..\users\working_with_resources.dita" xtrc="navtitle:1">Working with Resources</navtitle>
		<searchtitle class="- topic/searchtitle " xtrf="..\users\working_with_resources.dita" xtrc="searchtitle:1">Working with Resources</searchtitle>
	</titlealts>
	<shortdesc class="- topic/shortdesc " xtrf="..\users\working_with_resources.dita" xtrc="shortdesc:1">Explains how to do something.</shortdesc>
	<prolog class="- topic/prolog " xtrf="..\users\working_with_resources.dita" xtrc="prolog:1"/>
	<taskbody class="- topic/body task/taskbody " xtrf="..\users\working_with_resources.dita" xtrc="taskbody:1">
		<context class="- topic/section task/context " xtrf="..\users\working_with_resources.dita" xtrc="context:1">
			<p class="- topic/p " xtrf="..\users\working_with_resources.dita" xtrc="p:1">Once every 6000 kilometers or three months, change the oil in your car. This will help keep the engine in good condition. </p>
			<p class="- topic/p " xtrf="..\users\working_with_resources.dita" xtrc="p:2">To change the oil:</p>
		</context>
		<steps class="- topic/ol task/steps " xtrf="..\users\working_with_resources.dita" xtrc="steps:1">
			<step class="- topic/li task/step " xtrf="..\users\working_with_resources.dita" xtrc="step:1">
				<cmd class="- topic/ph task/cmd " xtrf="..\users\working_with_resources.dita" xtrc="cmd:1">Remove the old oil filter.</cmd>
			</step>
			<step class="- topic/li task/step " xtrf="..\users\working_with_resources.dita" xtrc="step:2">
				<cmd class="- topic/ph task/cmd " xtrf="..\users\working_with_resources.dita" xtrc="cmd:2">Drain the old oil.</cmd>
			</step>
			<step class="- topic/li task/step " xtrf="..\users\working_with_resources.dita" xtrc="step:3">
				<cmd class="- topic/ph task/cmd " xtrf="..\users\working_with_resources.dita" xtrc="cmd:3">Install a new oil filter and gasket.</cmd>
			</step>
			<step class="- topic/li task/step " xtrf="..\users\working_with_resources.dita" xtrc="step:4">
				<cmd class="- topic/ph task/cmd " xtrf="..\users\working_with_resources.dita" xtrc="cmd:4">Add new oil to the engine.</cmd>
			</step>
			<step class="- topic/li task/step " xtrf="..\users\working_with_resources.dita" xtrc="step:5">
				<cmd class="- topic/ph task/cmd " xtrf="..\users\working_with_resources.dita" xtrc="cmd:5">Check the air filter and replace or clean it.</cmd>
			</step>
			<step class="- topic/li task/step " xtrf="..\users\working_with_resources.dita" xtrc="step:6">
				<cmd class="- topic/ph task/cmd " xtrf="..\users\working_with_resources.dita" xtrc="cmd:6">Top up the windshield washer fluid.</cmd>
			</step>
		</steps>
	</taskbody>
<related-links class="- topic/related-links "><linkpool class="- topic/linkpool " xtrf="..\toc.ditamap" xtrc="topicref:400" mapkeyref="cdo"><link class="- topic/link " mapclass="- map/topicref " type="task" xtrc="topicref:368" xtrf="..\toc.ditamap" href="../users/using_the_sessions_view.xml" role="parent"><linktext class="- topic/linktext ">Using the Sessions View</linktext><desc class="- topic/desc ">Explains how to do something.</desc></link><linkpool class="- topic/linkpool " xtrf="..\toc.ditamap" xtrc="topicref:400"><link class="- topic/link " mapclass="- map/topicref " type="task" xtrc="topicref:401" xtrf="..\toc.ditamap" href="../users/creating_new_resources.xml" role="child"><linktext class="- topic/linktext ">Creating New Resources</linktext><desc class="- topic/desc ">Explains how to do something.</desc></link><link class="- topic/link " mapclass="- map/topicref " type="task" xtrc="topicref:402" xtrf="..\toc.ditamap" href="../users/loading_existing_resources.xml" role="child"><linktext class="- topic/linktext ">Loading Existing Resources</linktext><desc class="- topic/desc ">Explains how to do something.</desc></link><link class="- topic/link " mapclass="- map/topicref " type="task" xtrc="topicref:403" xtrf="..\toc.ditamap" href="../users/importing_resources.xml" role="child"><linktext class="- topic/linktext ">Importing Resources</linktext><desc class="- topic/desc ">Explains how to do something.</desc></link><link class="- topic/link " mapclass="- map/topicref " type="task" xtrc="topicref:405" xtrf="..\toc.ditamap" href="../users/exporting_resources.xml" role="child"><linktext class="- topic/linktext ">Exporting Resources</linktext><desc class="- topic/desc ">Explains how to do something.</desc></link><link class="- topic/link " mapclass="- map/topicref " type="task" xtrc="topicref:407" xtrf="..\toc.ditamap" href="../users/opening_an_editor_for_a_resource.xml" role="child"><linktext class="- topic/linktext ">Opening an Editor for a Resource</linktext><desc class="- topic/desc ">Explains how to do something.</desc></link></linkpool></linkpool></related-links>
</task>